grabify/__init__.py
grabify/__main__.py
grabify/cli.py
grabify/config.py
grabify/utils.py
grabify_cli-1.1.0.dist-info/METADATA
grabify_cli-1.1.0.dist-info/WHEEL
grabify_cli-1.1.0.dist-info/entry_points.txt
grabify_cli-1.1.0.dist-info/licenses/LICENSE
grabify_cli-1.1.0.dist-info/RECORD
