Metadata-Version: 2.1
Name: grabify-cli
Version: 1.1.0
Summary: 🎼 A command-line tool that allows you to download artwork and metadata from Spotify tracks and albums without authentication.
Project-URL: Homepage, https://github.com/woidzero/grabify
Project-URL: Documentation, https://github.com/woidzero/grabify#readme
Project-URL: Issues, https://github.com/woidzero/grabify/issues
Project-URL: Source, https://github.com/woidzero/grabify
Author: woidzero
License-Expression: MIT
License-File: LICENSE
Keywords: cli,command-line,console,grabify,spotify,spotipy
Classifier: Development Status :: 5 - Production/Stable
Classifier: Environment :: Console
Classifier: License :: OSI Approved :: MIT License
Classifier: Natural Language :: English
Classifier: Operating System :: OS Independent
Classifier: Programming Language :: Python
Classifier: Programming Language :: Python :: 3.7
Classifier: Programming Language :: Python :: 3.8
Classifier: Programming Language :: Python :: 3.9
Classifier: Programming Language :: Python :: 3.10
Classifier: Programming Language :: Python :: 3.11
Classifier: Programming Language :: Python :: Implementation :: CPython
Classifier: Programming Language :: Python :: Implementation :: PyPy
Requires-Python: >=3.7
Requires-Dist: beautifulsoup4
Requires-Dist: click
Requires-Dist: lxml
Requires-Dist: requests
Requires-Dist: rich
